[
  { "exercise_id": "ex_noun_weg_001", "word_id": "noun_weg", "type": "translate_word", "difficulty": 1, "question": { "de": "der Weg", "prompt_en": "What does this word mean?" }, "correct_answer": "the way / path", "wrong_answers": ["the street", "the road", "the direction", "the route"], "explanation_en": "'Weg' means 'way', 'path', or 'route'. It is a masculine noun taking the article 'der'." },
  { "exercise_id": "ex_noun_weg_002", "word_id": "noun_weg", "type": "article_choice", "difficulty": 1, "question": { "de": "_____ Weg durch den Wald ist schön.", "en": "The path through the forest is beautiful." }, "correct_answer": "Der", "wrong_answers": ["Die", "Das", "Ein", "Den"], "explanation_en": "'Weg' is masculine. As the nominative subject, it takes 'der'." },
  { "exercise_id": "ex_noun_weg_003", "word_id": "noun_weg", "type": "fill_blank", "difficulty": 1, "question": { "de": "Der _____ zur Schule dauert zehn Minuten.", "en": "The way to school takes ten minutes." }, "correct_answer": "Weg", "wrong_answers": ["Pfad", "Eingang", "Ausgang", "Umweg"], "explanation_en": "'Weg' means 'way' or 'path'. It is the masculine subject, used with 'der'." },
  { "exercise_id": "ex_noun_weg_004", "word_id": "noun_weg", "type": "fill_blank", "difficulty": 2, "question": { "de": "Ich kenne den _____ leider nicht.", "en": "I'm afraid I don't know the way." }, "correct_answer": "Weg", "wrong_answers": ["Pfad", "Eingang", "Ausgang", "Umweg"], "explanation_en": "'kennen' takes the accusative. 'den Weg' — masculine accusative uses 'den'. The noun is unchanged." },

  { "exercise_id": "ex_noun_platz_001", "word_id": "noun_platz", "type": "translate_word", "difficulty": 1, "question": { "de": "der Platz", "prompt_en": "What does this word mean?" }, "correct_answer": "the place / seat / square", "wrong_answers": ["the room", "the space", "the area", "the corner"], "explanation_en": "'Platz' means 'place', 'seat', or 'square'. It is a masculine noun taking the article 'der'." },
  { "exercise_id": "ex_noun_platz_002", "word_id": "noun_platz", "type": "article_choice", "difficulty": 1, "question": { "de": "_____ Platz vor dem Rathaus ist sehr groß.", "en": "The square in front of the town hall is very large." }, "correct_answer": "Der", "wrong_answers": ["Die", "Das", "Ein", "Den"], "explanation_en": "'Platz' is masculine. As the nominative subject, it takes 'der'." },
  { "exercise_id": "ex_noun_platz_003", "word_id": "noun_platz", "type": "fill_blank", "difficulty": 1, "question": { "de": "Der _____ neben mir ist noch frei.", "en": "The seat next to me is still free." }, "correct_answer": "Platz", "wrong_answers": ["Tisch", "Stuhl", "Raum", "Bereich"], "explanation_en": "'Platz' means 'seat' or 'place'. It is the masculine subject, used with 'der'." },
  { "exercise_id": "ex_noun_platz_004", "word_id": "noun_platz", "type": "fill_blank", "difficulty": 2, "question": { "de": "Darf ich diesen _____ nehmen?", "en": "May I take this seat?" }, "correct_answer": "Platz", "wrong_answers": ["Tisch", "Stuhl", "Raum", "Bereich"], "explanation_en": "'nehmen' takes the accusative. 'diesen Platz' — masculine accusative uses 'diesen' before the unchanged noun." },

  { "exercise_id": "ex_noun_seite_001", "word_id": "noun_seite", "type": "translate_word", "difficulty": 1, "question": { "de": "die Seite", "prompt_en": "What does this word mean?" }, "correct_answer": "the side / page", "wrong_answers": ["the front", "the back", "the edge", "the line"], "explanation_en": "'Seite' means 'side' or 'page'. It is a feminine noun taking the article 'die'." },
  { "exercise_id": "ex_noun_seite_002", "word_id": "noun_seite", "type": "article_choice", "difficulty": 1, "question": { "de": "_____ Seite des Buches ist beschädigt.", "en": "The page of the book is damaged." }, "correct_answer": "Die", "wrong_answers": ["Der", "Das", "Eine", "Den"], "explanation_en": "'Seite' is feminine. As the nominative subject, it takes 'die'." },
  { "exercise_id": "ex_noun_seite_003", "word_id": "noun_seite", "type": "fill_blank", "difficulty": 1, "question": { "de": "Die _____ drei enthält die Antwort.", "en": "Page three contains the answer." }, "correct_answer": "Seite", "wrong_answers": ["Zeile", "Spalte", "Zeitung", "Hälfte"], "explanation_en": "'Seite' means 'page'. It is the feminine subject, used with 'die'." },
  { "exercise_id": "ex_noun_seite_004", "word_id": "noun_seite", "type": "fill_blank", "difficulty": 2, "question": { "de": "Bitte lest die nächste _____ im Buch.", "en": "Please read the next page in the book." }, "correct_answer": "Seite", "wrong_answers": ["Zeile", "Spalte", "Hälfte", "Ecke"], "explanation_en": "'lesen' takes the accusative. Feminine nouns look the same in nominative and accusative: 'die nächste Seite'." },

  { "exercise_id": "ex_noun_art_001", "word_id": "noun_art", "type": "translate_word", "difficulty": 1, "question": { "de": "die Art", "prompt_en": "What does this word mean?" }, "correct_answer": "the type / kind / way", "wrong_answers": ["the style", "the method", "the form", "the sort"], "explanation_en": "'Art' means 'type', 'kind', or 'way of doing something'. It is a feminine noun taking the article 'die'." },
  { "exercise_id": "ex_noun_art_002", "word_id": "noun_art", "type": "article_choice", "difficulty": 1, "question": { "de": "_____ Art, wie er spricht, gefällt mir.", "en": "The way he speaks appeals to me." }, "correct_answer": "Die", "wrong_answers": ["Der", "Das", "Eine", "Den"], "explanation_en": "'Art' is feminine. As the nominative subject, it takes 'die'." },
  { "exercise_id": "ex_noun_art_003", "word_id": "noun_art", "type": "fill_blank", "difficulty": 1, "question": { "de": "Diese _____ zu lernen ist sehr effektiv.", "en": "This way of learning is very effective." }, "correct_answer": "Art", "wrong_answers": ["Methode", "Form", "Weise", "Strategie"], "explanation_en": "'Art' means 'way' or 'kind'. After 'diese' (feminine nominative), the noun is unchanged." },
  { "exercise_id": "ex_noun_art_004", "word_id": "noun_art", "type": "fill_blank", "difficulty": 2, "question": { "de": "Es gibt viele verschiedene _____ von Tieren.", "en": "There are many different kinds of animals." }, "correct_answer": "Arten", "wrong_answers": ["Methoden", "Formen", "Weisen", "Typen"], "explanation_en": "The plural of 'Art' is 'Arten'. 'viele verschiedene Arten' uses the plural accusative form of the noun." },

  { "exercise_id": "ex_noun_name_001", "word_id": "noun_name", "type": "translate_word", "difficulty": 1, "question": { "de": "der Name", "prompt_en": "What does this word mean?" }, "correct_answer": "the name", "wrong_answers": ["the word", "the title", "the label", "the number"], "explanation_en": "'Name' means 'name'. It is a masculine noun — and a weak noun (N-Deklination), taking the article 'der'." },
  { "exercise_id": "ex_noun_name_002", "word_id": "noun_name", "type": "article_choice", "difficulty": 1, "question": { "de": "_____ Name des Restaurants ist unbekannt.", "en": "The name of the restaurant is unknown." }, "correct_answer": "Der", "wrong_answers": ["Die", "Das", "Ein", "Den"], "explanation_en": "'Name' is masculine. As the nominative subject, it takes 'der'." },
  { "exercise_id": "ex_noun_name_003", "word_id": "noun_name", "type": "fill_blank", "difficulty": 1, "question": { "de": "Der _____ der Stadt ist sehr bekannt.", "en": "The name of the city is very well known." }, "correct_answer": "Name", "wrong_answers": ["Titel", "Begriff", "Buchstabe", "Ausdruck"], "explanation_en": "'Name' means 'name'. It is the masculine subject, used with 'der'." },
  { "exercise_id": "ex_noun_name_004", "word_id": "noun_name", "type": "fill_blank", "difficulty": 2, "question": { "de": "Ich habe seinen _____ vergessen.", "en": "I have forgotten his name." }, "correct_answer": "Namen", "wrong_answers": ["Titel", "Begriff", "Buchstaben", "Ausdruck"], "explanation_en": "'Name' is a weak masculine noun. In the accusative, it adds -n: 'seinen Namen'. This is the N-Deklination pattern." },

  { "exercise_id": "ex_noun_kopf_001", "word_id": "noun_kopf", "type": "translate_word", "difficulty": 1, "question": { "de": "der Kopf", "prompt_en": "What does this word mean?" }, "correct_answer": "the head", "wrong_answers": ["the face", "the hair", "the neck", "the brain"], "explanation_en": "'Kopf' means 'head'. It is a masculine noun taking the article 'der'." },
  { "exercise_id": "ex_noun_kopf_002", "word_id": "noun_kopf", "type": "article_choice", "difficulty": 1, "question": { "de": "_____ Kopf tut mir weh.", "en": "My head hurts." }, "correct_answer": "Der", "wrong_answers": ["Die", "Das", "Ein", "Den"], "explanation_en": "'Kopf' is masculine. As the nominative subject, it takes 'der'." },
  { "exercise_id": "ex_noun_kopf_003", "word_id": "noun_kopf", "type": "fill_blank", "difficulty": 1, "question": { "de": "Der _____ ist der oberste Teil des Körpers.", "en": "The head is the uppermost part of the body." }, "correct_answer": "Kopf", "wrong_answers": ["Hals", "Arm", "Rücken", "Bauch"], "explanation_en": "'Kopf' means 'head'. It is the masculine subject, used with 'der'." },
  { "exercise_id": "ex_noun_kopf_004", "word_id": "noun_kopf", "type": "fill_blank", "difficulty": 2, "question": { "de": "Er schüttelt den _____ und sagt nichts.", "en": "He shakes his head and says nothing." }, "correct_answer": "Kopf", "wrong_answers": ["Arm", "Hals", "Finger", "Rücken"], "explanation_en": "'schütteln' takes the accusative. 'den Kopf' — masculine accusative uses 'den'. The noun is unchanged." },

  { "exercise_id": "ex_noun_hand_001", "word_id": "noun_hand", "type": "translate_word", "difficulty": 1, "question": { "de": "die Hand", "prompt_en": "What does this word mean?" }, "correct_answer": "the hand", "wrong_answers": ["the arm", "the finger", "the wrist", "the fist"], "explanation_en": "'Hand' means 'hand'. It is a feminine noun taking the article 'die'." },
  { "exercise_id": "ex_noun_hand_002", "word_id": "noun_hand", "type": "article_choice", "difficulty": 1, "question": { "de": "_____ Hand ist sehr kalt.", "en": "The hand is very cold." }, "correct_answer": "Die", "wrong_answers": ["Der", "Das", "Eine", "Den"], "explanation_en": "'Hand' is feminine. As the nominative subject, it takes 'die'." },
  { "exercise_id": "ex_noun_hand_003", "word_id": "noun_hand", "type": "fill_blank", "difficulty": 1, "question": { "de": "Die _____ des Kindes ist sehr klein.", "en": "The child's hand is very small." }, "correct_answer": "Hand", "wrong_answers": ["Arm", "Finger", "Schulter", "Faust"], "explanation_en": "'Hand' means 'hand'. It is the feminine subject, used with 'die'." },
  { "exercise_id": "ex_noun_hand_004", "word_id": "noun_hand", "type": "fill_blank", "difficulty": 2, "question": { "de": "Er gibt mir die _____ zur Begrüßung.", "en": "He gives me his hand in greeting." }, "correct_answer": "Hand", "wrong_answers": ["Arm", "Finger", "Schulter", "Faust"], "explanation_en": "'geben' takes a dative object (mir) and accusative object (die Hand). Feminine nouns look the same in nominative and accusative: 'die Hand'." },

  { "exercise_id": "ex_noun_herz_001", "word_id": "noun_herz", "type": "translate_word", "difficulty": 1, "question": { "de": "das Herz", "prompt_en": "What does this word mean?" }, "correct_answer": "the heart", "wrong_answers": ["the liver", "the lung", "the brain", "the stomach"], "explanation_en": "'Herz' means 'heart'. It is a neuter noun taking the article 'das'." },
  { "exercise_id": "ex_noun_herz_002", "word_id": "noun_herz", "type": "article_choice", "difficulty": 1, "question": { "de": "_____ Herz schlägt sehr schnell.", "en": "The heart is beating very fast." }, "correct_answer": "Das", "wrong_answers": ["Der", "Die", "Ein", "Den"], "explanation_en": "'Herz' is neuter. As the nominative subject, it takes 'das'." },
  { "exercise_id": "ex_noun_herz_003", "word_id": "noun_herz", "type": "fill_blank", "difficulty": 1, "question": { "de": "Das _____ ist ein wichtiges Organ.", "en": "The heart is an important organ." }, "correct_answer": "Herz", "wrong_answers": ["Gehirn", "Lunge", "Leber", "Magen"], "explanation_en": "'Herz' means 'heart'. It is the neuter subject, used with 'das'." },
  { "exercise_id": "ex_noun_herz_004", "word_id": "noun_herz", "type": "fill_blank", "difficulty": 2, "question": { "de": "Er hat ein großes _____ und hilft immer anderen.", "en": "He has a big heart and always helps others." }, "correct_answer": "Herz", "wrong_answers": ["Gehirn", "Talent", "Lächeln", "Gefühl"], "explanation_en": "After 'ein großes' (neuter accusative adjective), 'Herz' is unchanged — neuter nominative and accusative are identical." },

  { "exercise_id": "ex_noun_stimme_001", "word_id": "noun_stimme", "type": "translate_word", "difficulty": 1, "question": { "de": "die Stimme", "prompt_en": "What does this word mean?" }, "correct_answer": "the voice", "wrong_answers": ["the sound", "the noise", "the speech", "the tone"], "explanation_en": "'Stimme' means 'voice'. It is a feminine noun taking the article 'die'." },
  { "exercise_id": "ex_noun_stimme_002", "word_id": "noun_stimme", "type": "article_choice", "difficulty": 1, "question": { "de": "_____ Stimme ist sehr laut.", "en": "The voice is very loud." }, "correct_answer": "Die", "wrong_answers": ["Der", "Das", "Eine", "Den"], "explanation_en": "'Stimme' is feminine. As the nominative subject, it takes 'die'." },
  { "exercise_id": "ex_noun_stimme_003", "word_id": "noun_stimme", "type": "fill_blank", "difficulty": 1, "question": { "de": "Die _____ des Sängers ist wunderschön.", "en": "The singer's voice is wonderful." }, "correct_answer": "Stimme", "wrong_answers": ["Melodie", "Musik", "Sprache", "Aussprache"], "explanation_en": "'Stimme' means 'voice'. It is the feminine subject, used with 'die'." },
  { "exercise_id": "ex_noun_stimme_004", "word_id": "noun_stimme", "type": "fill_blank", "difficulty": 2, "question": { "de": "Ich erkenne seine _____ sofort.", "en": "I recognise his voice immediately." }, "correct_answer": "Stimme", "wrong_answers": ["Sprache", "Aussprache", "Melodie", "Art"], "explanation_en": "'erkennen' takes the accusative. Feminine nouns look the same in nominative and accusative: 'seine Stimme'." },

  { "exercise_id": "ex_noun_gesicht_001", "word_id": "noun_gesicht", "type": "translate_word", "difficulty": 1, "question": { "de": "das Gesicht", "prompt_en": "What does this word mean?" }, "correct_answer": "the face", "wrong_answers": ["the head", "the expression", "the cheek", "the profile"], "explanation_en": "'Gesicht' means 'face'. It is a neuter noun taking the article 'das'." },
  { "exercise_id": "ex_noun_gesicht_002", "word_id": "noun_gesicht", "type": "article_choice", "difficulty": 1, "question": { "de": "_____ Gesicht des Kindes ist sehr süß.", "en": "The child's face is very sweet." }, "correct_answer": "Das", "wrong_answers": ["Der", "Die", "Ein", "Den"], "explanation_en": "'Gesicht' is neuter. As the nominative subject, it takes 'das'." },
  { "exercise_id": "ex_noun_gesicht_003", "word_id": "noun_gesicht", "type": "fill_blank", "difficulty": 1, "question": { "de": "Das _____ zeigt, was er fühlt.", "en": "The face shows what he feels." }, "correct_answer": "Gesicht", "wrong_answers": ["Verhalten", "Blick", "Ausdruck", "Aussehen"], "explanation_en": "'Gesicht' means 'face'. It is the neuter subject, used with 'das'." },
  { "exercise_id": "ex_noun_gesicht_004", "word_id": "noun_gesicht", "type": "fill_blank", "difficulty": 2, "question": { "de": "Sie wäscht ihr _____ mit kaltem Wasser.", "en": "She washes her face with cold water." }, "correct_answer": "Gesicht", "wrong_answers": ["Haar", "Blick", "Aussehen", "Kinn"], "explanation_en": "After 'ihr' (possessive, neuter accusative), 'Gesicht' is unchanged — neuter nominative and accusative are identical." },

  { "exercise_id": "ex_noun_zug_001", "word_id": "noun_zug", "type": "translate_word", "difficulty": 1, "question": { "de": "der Zug", "prompt_en": "What does this word mean?" }, "correct_answer": "the train", "wrong_answers": ["the bus", "the tram", "the underground", "the plane"], "explanation_en": "'Zug' means 'train'. It is a masculine noun taking the article 'der'." },
  { "exercise_id": "ex_noun_zug_002", "word_id": "noun_zug", "type": "article_choice", "difficulty": 1, "question": { "de": "_____ Zug fährt um 9 Uhr ab.", "en": "The train departs at 9 o'clock." }, "correct_answer": "Der", "wrong_answers": ["Die", "Das", "Ein", "Den"], "explanation_en": "'Zug' is masculine. As the nominative subject, it takes 'der'." },
  { "exercise_id": "ex_noun_zug_003", "word_id": "noun_zug", "type": "fill_blank", "difficulty": 1, "question": { "de": "Der _____ nach Berlin fährt von Gleis drei.", "en": "The train to Berlin leaves from platform three." }, "correct_answer": "Zug", "wrong_answers": ["Bus", "Tram", "Fähre", "Flug"], "explanation_en": "'Zug' means 'train'. It is the masculine subject, used with 'der'." },
  { "exercise_id": "ex_noun_zug_004", "word_id": "noun_zug", "type": "fill_blank", "difficulty": 2, "question": { "de": "Ich nehme den nächsten _____ nach Hamburg.", "en": "I am taking the next train to Hamburg." }, "correct_answer": "Zug", "wrong_answers": ["Bus", "Tram", "Fähre", "Flug"], "explanation_en": "'nehmen' takes the accusative. 'den nächsten Zug' — masculine accusative uses 'den'." },

  { "exercise_id": "ex_noun_preis_001", "word_id": "noun_preis", "type": "translate_word", "difficulty": 1, "question": { "de": "der Preis", "prompt_en": "What does this word mean?" }, "correct_answer": "the price / prize", "wrong_answers": ["the cost", "the fee", "the value", "the discount"], "explanation_en": "'Preis' means both 'price' and 'prize'. It is a masculine noun taking the article 'der'." },
  { "exercise_id": "ex_noun_preis_002", "word_id": "noun_preis", "type": "article_choice", "difficulty": 1, "question": { "de": "_____ Preis ist sehr hoch.", "en": "The price is very high." }, "correct_answer": "Der", "wrong_answers": ["Die", "Das", "Ein", "Den"], "explanation_en": "'Preis' is masculine. As the nominative subject, it takes 'der'." },
  { "exercise_id": "ex_noun_preis_003", "word_id": "noun_preis", "type": "fill_blank", "difficulty": 1, "question": { "de": "Der _____ für das Ticket ist gestiegen.", "en": "The price for the ticket has gone up." }, "correct_answer": "Preis", "wrong_answers": ["Betrag", "Lohn", "Rabatt", "Wert"], "explanation_en": "'Preis' means 'price'. It is the masculine subject, used with 'der'." },
  { "exercise_id": "ex_noun_preis_004", "word_id": "noun_preis", "type": "fill_blank", "difficulty": 2, "question": { "de": "Sie hat den ersten _____ im Wettbewerb gewonnen.", "en": "She won first prize in the competition." }, "correct_answer": "Preis", "wrong_answers": ["Pokal", "Lohn", "Betrag", "Titel"], "explanation_en": "'gewinnen' takes the accusative. 'den ersten Preis' — masculine accusative uses 'den'." }
]
